{
      "annotations": {
         "list": [ ]
      },
      "links": [
         {
            "asDropdown": true,
            "includeVars": true,
            "keepTime": true,
            "tags": [
               "snowflake-mixin"
            ],
            "title": "All dashboards",
            "type": "dashboards"
         },
         {
            "keepTime": true,
            "title": "Snowflake data ownership",
            "type": "link",
            "url": "/d/snowflake_data_ownership"
         }
      ],
      "panels": [
         {
            "collapsed": false,
            "gridPos": {
               "h": 1,
               "w": 0,
               "x": 0,
               "y": 0
            },
            "id": 1,
            "panels": [ ],
            "title": "Overview",
            "type": "row"
         },
         {
            "datasource": {
               "type": "datasource",
               "uid": "-- Mixed --"
            },
            "description": "Percentage of total login attempts that were successful.",
            "fieldConfig": {
               "defaults": {
                  "max": 1,
                  "min": 0,
                  "thresholds": {
                     "steps": [
                        {
                           "color": "red",
                           "value": 0
                        },
                        {
                           "color": "yellow",
                           "value": 0.59999999999999998
                        },
                        {
                           "color": "green",
                           "value": 0.80000000000000004
                        }
                     ]
                  },
                  "unit": "percentunit"
               }
            },
            "gridPos": {
               "h": 8,
               "w": 12,
               "x": 0,
               "y": 1
            },
            "id": 2,
            "options": {
               "reduceOptions": {
                  "calcs": [
                     "lastNotNull"
                  ],
                  "fields": "",
                  "limit": 1,
                  "values": false
               },
               "showThresholdLabels": false,
               "showThresholdMarkers": false
            },
            "pluginVersion": "v11.4.0",
            "targets": [
               {
                  "datasource": {
                     "type": "prometheus",
                     "uid": "${datasource}"
                  },
                  "expr": "sum by (job,instance) (snowflake_successful_login_rate{job=\"integrations/snowflake\",job=~\"$job\",instance=~\"$instance\"}) / sum by (job,instance) (snowflake_login_rate{job=\"integrations/snowflake\",job=~\"$job\",instance=~\"$instance\"})",
                  "format": "time_series",
                  "instant": false,
                  "legendFormat": "{{instance}} - Successful",
                  "refId": "Successful login attempts"
               }
            ],
            "title": "Successful login attempts",
            "type": "gauge"
         },
         {
            "datasource": {
               "type": "datasource",
               "uid": "-- Mixed --"
            },
            "description": "Percentage of total login attempts that failed.",
            "fieldConfig": {
               "defaults": {
                  "max": 1,
                  "min": 0,
                  "thresholds": {
                     "steps": [
                        {
                           "color": "green"
                        },
                        {
                           "color": "#EAB839",
                           "value": 0.20000000000000001
                        },
                        {
                           "color": "red",
                           "value": 0.40000000000000002
                        }
                     ]
                  },
                  "unit": "percentunit"
               }
            },
            "gridPos": {
               "h": 8,
               "w": 12,
               "x": 12,
               "y": 1
            },
            "id": 3,
            "options": {
               "reduceOptions": {
                  "calcs": [
                     "lastNotNull"
                  ],
                  "fields": "",
                  "values": false
               },
               "showThresholdLabels": false,
               "showThresholdMarkers": false
            },
            "pluginVersion": "v11.4.0",
            "targets": [
               {
                  "datasource": {
                     "type": "prometheus",
                     "uid": "${datasource}"
                  },
                  "expr": "sum by (job,instance) (snowflake_failed_login_rate{job=\"integrations/snowflake\",job=~\"$job\",instance=~\"$instance\"}) / sum by (job,instance) (snowflake_login_rate{job=\"integrations/snowflake\",job=~\"$job\",instance=~\"$instance\"})",
                  "format": "time_series",
                  "instant": false,
                  "legendFormat": "{{instance}} - Failed",
                  "refId": "Failed login attempts"
               }
            ],
            "title": "Failed login attempts",
            "type": "gauge"
         },
         {
            "datasource": {
               "type": "prometheus",
               "uid": "${datasource}"
            },
            "description": "Login attempt rate over the last 24 hours.",
            "fieldConfig": {
               "defaults": {
                  "custom": {
                     "fillOpacity": 30,
                     "gradientMode": "opacity",
                     "lineInterpolation": "smooth",
                     "lineWidth": 2,
                     "showPoints": "never"
                  },
                  "unit": "logins/hr"
               }
            },
            "gridPos": {
               "h": 8,
               "w": 24,
               "x": 0,
               "y": 9
            },
            "id": 4,
            "options": {
               "legend": {
                  "calcs": [ ],
                  "displayMode": "list"
               },
               "tooltip": {
                  "mode": "multi",
                  "sort": "desc"
               }
            },
            "pluginVersion": "v11.0.0",
            "targets": [
               {
                  "datasource": {
                     "type": "prometheus",
                     "uid": "${datasource}"
                  },
                  "expr": "sum by (job,instance) (snowflake_login_rate{job=\"integrations/snowflake\",job=~\"$job\",instance=~\"$instance\"})",
                  "format": "time_series",
                  "instant": false,
                  "legendFormat": "{{instance}} - Total",
                  "refId": "Login attempts total"
               },
               {
                  "datasource": {
                     "type": "prometheus",
                     "uid": "${datasource}"
                  },
                  "expr": "sum by (job,instance) (snowflake_failed_login_rate{job=\"integrations/snowflake\",job=~\"$job\",instance=~\"$instance\"})",
                  "format": "time_series",
                  "instant": false,
                  "legendFormat": "{{instance}} - Failed",
                  "refId": "Login attempts failed"
               },
               {
                  "datasource": {
                     "type": "prometheus",
                     "uid": "${datasource}"
                  },
                  "expr": "sum by (job,instance) (snowflake_successful_login_rate{job=\"integrations/snowflake\",job=~\"$job\",instance=~\"$instance\"})",
                  "format": "time_series",
                  "instant": false,
                  "legendFormat": "{{instance}} - Successful",
                  "refId": "Login attempts successful"
               }
            ],
            "title": "Login attempts",
            "type": "timeseries"
         },
         {
            "datasource": {
               "type": "prometheus",
               "uid": "${datasource}"
            },
            "description": "Warehouse query activity for the warehouse selected by the Warehouse selector.",
            "fieldConfig": {
               "defaults": {
                  "custom": {
                     "fillOpacity": 30,
                     "gradientMode": "opacity",
                     "lineInterpolation": "smooth",
                     "lineWidth": 2,
                     "showPoints": "never"
                  },
                  "unit": "percentunit"
               }
            },
            "gridPos": {
               "h": 8,
               "w": 12,
               "x": 0,
               "y": 17
            },
            "id": 5,
            "options": {
               "legend": {
                  "calcs": [ ],
                  "displayMode": "list"
               },
               "tooltip": {
                  "mode": "multi",
                  "sort": "desc"
               }
            },
            "pluginVersion": "v11.0.0",
            "targets": [
               {
                  "datasource": {
                     "type": "prometheus",
                     "uid": "${datasource}"
                  },
                  "expr": "snowflake_warehouse_executed_queries{job=\"integrations/snowflake\",job=~\"$job\",instance=~\"$instance\", name=~\"$warehouse\"}",
                  "format": "time_series",
                  "instant": false,
                  "legendFormat": "{{instance}} - {{name}} - Executed query load",
                  "refId": "Warehouse activity executed queries"
               },
               {
                  "datasource": {
                     "type": "prometheus",
                     "uid": "${datasource}"
                  },
                  "expr": "snowflake_warehouse_overloaded_queue_size{job=\"integrations/snowflake\",job=~\"$job\",instance=~\"$instance\", name=~\"$warehouse\"}",
                  "format": "time_series",
                  "instant": false,
                  "legendFormat": "{{instance}} - {{name}} - Overloaded queue load",
                  "refId": "Warehouse activity overloaded queue load"
               },
               {
                  "datasource": {
                     "type": "prometheus",
                     "uid": "${datasource}"
                  },
                  "expr": "snowflake_warehouse_provisioning_queue_size{job=\"integrations/snowflake\",job=~\"$job\",instance=~\"$instance\", name=~\"$warehouse\"}",
                  "format": "time_series",
                  "instant": false,
                  "legendFormat": "{{instance}} - {{name}} - Provisioning queue load",
                  "refId": "Warehouse activity provisioning queue load"
               },
               {
                  "datasource": {
                     "type": "prometheus",
                     "uid": "${datasource}"
                  },
                  "expr": "snowflake_warehouse_blocked_queries{job=\"integrations/snowflake\",job=~\"$job\",instance=~\"$instance\", name=~\"$warehouse\"}",
                  "format": "time_series",
                  "instant": false,
                  "legendFormat": "{{instance}} - {{name}} - Blocked query load",
                  "refId": "Warehouse activity blocked query load"
               }
            ],
            "title": "Warehouse activity",
            "type": "timeseries"
         },
         {
            "datasource": {
               "type": "prometheus",
               "uid": "${datasource}"
            },
            "description": "Data storage used for the account.",
            "fieldConfig": {
               "defaults": {
                  "custom": {
                     "fillOpacity": 30,
                     "gradientMode": "opacity",
                     "lineInterpolation": "smooth",
                     "lineWidth": 2,
                     "showPoints": "never"
                  },
                  "unit": "bytes"
               }
            },
            "gridPos": {
               "h": 8,
               "w": 12,
               "x": 12,
               "y": 17
            },
            "id": 6,
            "options": {
               "legend": {
                  "calcs": [ ],
                  "displayMode": "list"
               },
               "tooltip": {
                  "mode": "multi",
                  "sort": "desc"
               }
            },
            "pluginVersion": "v11.0.0",
            "targets": [
               {
                  "datasource": {
                     "type": "prometheus",
                     "uid": "${datasource}"
                  },
                  "expr": "snowflake_storage_bytes{job=\"integrations/snowflake\",job=~\"$job\",instance=~\"$instance\"}",
                  "format": "time_series",
                  "instant": false,
                  "legendFormat": "{{instance}} - Storage",
                  "refId": "Account storage usage"
               },
               {
                  "datasource": {
                     "type": "prometheus",
                     "uid": "${datasource}"
                  },
                  "expr": "snowflake_stage_bytes{job=\"integrations/snowflake\",job=~\"$job\",instance=~\"$instance\"}",
                  "format": "time_series",
                  "instant": false,
                  "legendFormat": "{{instance}} - Stage",
                  "refId": "Account stage usage"
               },
               {
                  "datasource": {
                     "type": "prometheus",
                     "uid": "${datasource}"
                  },
                  "expr": "snowflake_failsafe_bytes{job=\"integrations/snowflake\",job=~\"$job\",instance=~\"$instance\"}",
                  "format": "time_series",
                  "instant": false,
                  "legendFormat": "{{instance}} - Failsafe",
                  "refId": "Account failsafe usage"
               }
            ],
            "title": "Account storage usage",
            "type": "timeseries"
         },
         {
            "collapsed": false,
            "gridPos": {
               "h": 1,
               "w": 0,
               "x": 0,
               "y": 25
            },
            "id": 7,
            "panels": [ ],
            "title": "Billing",
            "type": "row"
         },
         {
            "datasource": {
               "type": "prometheus",
               "uid": "${datasource}"
            },
            "description": "Compute billing usage for the account.",
            "fieldConfig": {
               "defaults": {
                  "custom": {
                     "fillOpacity": 30,
                     "gradientMode": "opacity",
                     "lineInterpolation": "smooth",
                     "lineWidth": 2,
                     "showPoints": "never",
                     "thresholdsStyle": {
                        "mode": "area"
                     }
                  },
                  "thresholds": {
                     "steps": [
                        {
                           "color": "transparent",
                           "value": null
                        },
                        {
                           "color": "orange",
                           "value": 80
                        },
                        {
                           "color": "red",
                           "value": 100
                        }
                     ]
                  },
                  "unit": "percent"
               }
            },
            "gridPos": {
               "h": 8,
               "w": 12,
               "x": 0,
               "y": 26
            },
            "id": 8,
            "options": {
               "legend": {
                  "calcs": [ ],
                  "displayMode": "list"
               },
               "tooltip": {
                  "mode": "multi",
                  "sort": "desc"
               }
            },
            "pluginVersion": "v11.0.0",
            "targets": [
               {
                  "datasource": {
                     "type": "prometheus",
                     "uid": "${datasource}"
                  },
                  "expr": "sum by (job,instance) (last_over_time(snowflake_used_compute_credits{job=\"integrations/snowflake\",job=~\"$job\",instance=~\"$instance\"}[24h]) / 5)",
                  "format": "time_series",
                  "instant": false,
                  "legendFormat": "{{instance}} - Compute usage",
                  "refId": "Compute credit usage percentage"
               }
            ],
            "title": "Compute billing usage",
            "type": "timeseries"
         },
         {
            "datasource": {
               "type": "prometheus",
               "uid": "${datasource}"
            },
            "description": "Cloud services billing usage for the account.",
            "fieldConfig": {
               "defaults": {
                  "custom": {
                     "fillOpacity": 30,
                     "gradientMode": "opacity",
                     "lineInterpolation": "smooth",
                     "lineWidth": 2,
                     "showPoints": "never",
                     "thresholdsStyle": {
                        "mode": "area"
                     }
                  },
                  "thresholds": {
                     "steps": [
                        {
                           "color": "transparent",
                           "value": null
                        },
                        {
                           "color": "orange",
                           "value": 80
                        },
                        {
                           "color": "red",
                           "value": 100
                        }
                     ]
                  },
                  "unit": "percent"
               }
            },
            "gridPos": {
               "h": 8,
               "w": 12,
               "x": 12,
               "y": 26
            },
            "id": 9,
            "options": {
               "legend": {
                  "calcs": [ ],
                  "displayMode": "list"
               },
               "tooltip": {
                  "mode": "multi",
                  "sort": "desc"
               }
            },
            "pluginVersion": "v11.0.0",
            "targets": [
               {
                  "datasource": {
                     "type": "prometheus",
                     "uid": "${datasource}"
                  },
                  "expr": "sum by (job,instance) (last_over_time(snowflake_used_cloud_services_credits{job=\"integrations/snowflake\",job=~\"$job\",instance=~\"$instance\"}[24h]) / 1)",
                  "format": "time_series",
                  "instant": false,
                  "legendFormat": "{{instance}} - Cloud services usage",
                  "refId": "Cloud services credit usage percentage"
               }
            ],
            "title": "Cloud services billing usage",
            "type": "timeseries"
         },
         {
            "datasource": {
               "type": "prometheus",
               "uid": "${datasource}"
            },
            "description": "Number of billing credits used by the account.",
            "fieldConfig": {
               "defaults": {
                  "custom": {
                     "axisLabel": "credits/hr",
                     "fillOpacity": 30,
                     "gradientMode": "opacity",
                     "lineInterpolation": "smooth",
                     "lineWidth": 2,
                     "showPoints": "never"
                  },
                  "unit": "none"
               }
            },
            "gridPos": {
               "h": 8,
               "w": 12,
               "x": 0,
               "y": 34
            },
            "id": 10,
            "options": {
               "legend": {
                  "asTable": true,
                  "calcs": [ ],
                  "displayMode": "list",
                  "placement": "right"
               },
               "tooltip": {
                  "mode": "multi",
                  "sort": "desc"
               }
            },
            "pluginVersion": "v11.0.0",
            "targets": [
               {
                  "datasource": {
                     "type": "prometheus",
                     "uid": "${datasource}"
                  },
                  "expr": "sum by (job,instance) (snowflake_used_compute_credits{job=\"integrations/snowflake\",job=~\"$job\",instance=~\"$instance\"})",
                  "format": "time_series",
                  "instant": false,
                  "legendFormat": "{{instance}} - Compute",
                  "refId": "Used compute credits"
               },
               {
                  "datasource": {
                     "type": "prometheus",
                     "uid": "${datasource}"
                  },
                  "expr": "sum by (job,instance) (snowflake_used_cloud_services_credits{job=\"integrations/snowflake\",job=~\"$job\",instance=~\"$instance\"})",
                  "format": "time_series",
                  "instant": false,
                  "legendFormat": "{{instance}} - Service",
                  "refId": "Used cloud services credits"
               }
            ],
            "title": "Average hourly credits used",
            "type": "timeseries"
         },
         {
            "datasource": {
               "type": "prometheus",
               "uid": "${datasource}"
            },
            "description": "Credits billed for automatic reclustering.",
            "fieldConfig": {
               "defaults": {
                  "custom": {
                     "axisLabel": "credits/hr",
                     "fillOpacity": 30,
                     "gradientMode": "opacity",
                     "lineInterpolation": "smooth",
                     "lineWidth": 2,
                     "showPoints": "never"
                  },
                  "unit": "none"
               }
            },
            "gridPos": {
               "h": 8,
               "w": 12,
               "x": 12,
               "y": 34
            },
            "id": 11,
            "options": {
               "legend": {
                  "asTable": true,
                  "calcs": [ ],
                  "displayMode": "list",
                  "placement": "right"
               },
               "tooltip": {
                  "mode": "multi",
                  "sort": "desc"
               }
            },
            "pluginVersion": "v11.0.0",
            "targets": [
               {
                  "datasource": {
                     "type": "prometheus",
                     "uid": "${datasource}"
                  },
                  "expr": "snowflake_auto_clustering_credits{job=\"integrations/snowflake\",job=~\"$job\",instance=~\"$instance\"}",
                  "format": "time_series",
                  "instant": false,
                  "legendFormat": "{{database_name}} - {{schema_name}} - {{table_name}}",
                  "refId": "Autoclustering credits used"
               }
            ],
            "title": "Autoclustering credits used",
            "type": "timeseries"
         },
         {
            "datasource": {
               "type": "prometheus",
               "uid": "${datasource}"
            },
            "description": "The top 5 services that have the highest compute credit usages.",
            "fieldConfig": {
               "overrides": [
                  {
                     "matcher": {
                        "id": "byName",
                        "options": "Credits"
                     },
                     "properties": [
                        {
                           "id": "unit",
                           "value": "credits/hr"
                        },
                        {
                           "id": "decimals",
                           "value": 2
                        }
                     ]
                  }
               ]
            },
            "gridPos": {
               "h": 8,
               "w": 12,
               "x": 0,
               "y": 42
            },
            "id": 12,
            "options": {
               "showHeader": true
            },
            "pluginVersion": "v11.0.0",
            "targets": [
               {
                  "datasource": {
                     "type": "prometheus",
                     "uid": "${datasource}"
                  },
                  "expr": "snowflake_used_compute_credits{job=\"integrations/snowflake\",job=~\"$job\",instance=~\"$instance\"}",
                  "format": "table",
                  "instant": true,
                  "legendFormat": "{{instance}}",
                  "refId": "Service compute credits used"
               }
            ],
            "title": "Top 5 service compute credits used",
            "transformations": [
               {
                  "id": "groupBy",
                  "options": {
                     "fields": {
                        "Value": {
                           "aggregations": [
                              "last"
                           ],
                           "operation": "aggregate"
                        },
                        "instance": {
                           "aggregations": [ ],
                           "operation": "groupby"
                        },
                        "service": {
                           "aggregations": [ ],
                           "operation": "groupby"
                        },
                        "service_type": {
                           "aggregations": [ ],
                           "operation": "groupby"
                        }
                     }
                  }
               },
               {
                  "id": "sortBy",
                  "options": {
                     "fields": { },
                     "sort": [
                        {
                           "desc": true,
                           "field": "Value (last)"
                        }
                     ]
                  }
               },
               {
                  "id": "limit",
                  "options": {
                     "limitField": 5
                  }
               },
               {
                  "id": "organize",
                  "options": {
                     "excludeByName": { },
                     "indexByName": { },
                     "renameByName": {
                        "Value (last)": "Credits",
                        "instance": "Instance",
                        "service": "Service",
                        "service_type": "Service Type"
                     }
                  }
               }
            ],
            "type": "table"
         },
         {
            "datasource": {
               "type": "prometheus",
               "uid": "${datasource}"
            },
            "description": "The top 5 services that have the highest compute credit usages.",
            "fieldConfig": {
               "overrides": [
                  {
                     "matcher": {
                        "id": "byName",
                        "options": "Credits"
                     },
                     "properties": [
                        {
                           "id": "unit",
                           "value": "credits/hr"
                        },
                        {
                           "id": "decimals",
                           "value": 2
                        }
                     ]
                  }
               ]
            },
            "gridPos": {
               "h": 8,
               "w": 12,
               "x": 12,
               "y": 42
            },
            "id": 13,
            "options": {
               "showHeader": true
            },
            "pluginVersion": "v11.0.0",
            "targets": [
               {
                  "datasource": {
                     "type": "prometheus",
                     "uid": "${datasource}"
                  },
                  "expr": "snowflake_used_cloud_services_credits{job=\"integrations/snowflake\",job=~\"$job\",instance=~\"$instance\"}",
                  "format": "table",
                  "instant": true,
                  "legendFormat": "{{instance}}",
                  "refId": "Service cloud service credits used"
               }
            ],
            "title": "Top 5 service cloud service credits used",
            "transformations": [
               {
                  "id": "groupBy",
                  "options": {
                     "fields": {
                        "Value": {
                           "aggregations": [
                              "last"
                           ],
                           "operation": "aggregate"
                        },
                        "instance": {
                           "aggregations": [ ],
                           "operation": "groupby"
                        },
                        "service": {
                           "aggregations": [ ],
                           "operation": "groupby"
                        },
                        "service_type": {
                           "aggregations": [ ],
                           "operation": "groupby"
                        }
                     }
                  }
               },
               {
                  "id": "sortBy",
                  "options": {
                     "fields": { },
                     "sort": [
                        {
                           "desc": true,
                           "field": "Value (last)"
                        }
                     ]
                  }
               },
               {
                  "id": "limit",
                  "options": {
                     "limitField": 5
                  }
               },
               {
                  "id": "organize",
                  "options": {
                     "excludeByName": { },
                     "indexByName": { },
                     "renameByName": {
                        "Value (last)": "Credits",
                        "instance": "Instance",
                        "service": "Service",
                        "service_type": "Service Type"
                     }
                  }
               }
            ],
            "type": "table"
         },
         {
            "datasource": {
               "type": "prometheus",
               "uid": "${datasource}"
            },
            "description": "The top 5 warehouses that have the highest compute credit usages.",
            "fieldConfig": {
               "overrides": [
                  {
                     "matcher": {
                        "id": "byName",
                        "options": "Credits"
                     },
                     "properties": [
                        {
                           "id": "unit",
                           "value": "credits/hr"
                        }
                     ]
                  }
               ]
            },
            "gridPos": {
               "h": 8,
               "w": 12,
               "x": 0,
               "y": 50
            },
            "id": 14,
            "options": {
               "showHeader": true
            },
            "pluginVersion": "v11.0.0",
            "targets": [
               {
                  "datasource": {
                     "type": "prometheus",
                     "uid": "${datasource}"
                  },
                  "expr": "snowflake_warehouse_used_compute_credits{job=\"integrations/snowflake\",job=~\"$job\",instance=~\"$instance\"}",
                  "format": "table",
                  "instant": true,
                  "legendFormat": "{{instance}}",
                  "refId": "Warehouse compute credits used"
               }
            ],
            "title": "Top 5 warehouse compute credits used",
            "transformations": [
               {
                  "id": "groupBy",
                  "options": {
                     "fields": {
                        "Value": {
                           "aggregations": [
                              "last"
                           ],
                           "operation": "aggregate"
                        },
                        "instance": {
                           "aggregations": [ ],
                           "operation": "groupby"
                        },
                        "name": {
                           "aggregations": [ ],
                           "operation": "groupby"
                        }
                     }
                  }
               },
               {
                  "id": "sortBy",
                  "options": {
                     "fields": { },
                     "sort": [
                        {
                           "desc": true,
                           "field": "Value (last)"
                        }
                     ]
                  }
               },
               {
                  "id": "limit",
                  "options": {
                     "limitField": 5
                  }
               },
               {
                  "id": "organize",
                  "options": {
                     "excludeByName": { },
                     "indexByName": { },
                     "renameByName": {
                        "Value (last)": "Credits",
                        "instance": "Instance",
                        "name": "Warehouse"
                     }
                  }
               }
            ],
            "type": "table"
         },
         {
            "datasource": {
               "type": "prometheus",
               "uid": "${datasource}"
            },
            "description": "The top 5 warehouses that have the highest services credit usages.",
            "fieldConfig": {
               "overrides": [
                  {
                     "matcher": {
                        "id": "byName",
                        "options": "Credits"
                     },
                     "properties": [
                        {
                           "id": "unit",
                           "value": "credits/hr"
                        },
                        {
                           "id": "decimals",
                           "value": 2
                        }
                     ]
                  }
               ]
            },
            "gridPos": {
               "h": 8,
               "w": 12,
               "x": 12,
               "y": 50
            },
            "id": 15,
            "options": {
               "showHeader": true
            },
            "pluginVersion": "v11.0.0",
            "targets": [
               {
                  "datasource": {
                     "type": "prometheus",
                     "uid": "${datasource}"
                  },
                  "expr": "snowflake_warehouse_used_cloud_service_credits{job=\"integrations/snowflake\",job=~\"$job\",instance=~\"$instance\"}",
                  "format": "table",
                  "instant": true,
                  "legendFormat": "{{instance}}",
                  "refId": "Warehouse cloud services credits used"
               }
            ],
            "title": "Top 5 warehouse cloud services credits used",
            "transformations": [
               {
                  "id": "groupBy",
                  "options": {
                     "fields": {
                        "Value": {
                           "aggregations": [
                              "last"
                           ],
                           "operation": "aggregate"
                        },
                        "instance": {
                           "aggregations": [ ],
                           "operation": "groupby"
                        },
                        "name": {
                           "aggregations": [ ],
                           "operation": "groupby"
                        }
                     }
                  }
               },
               {
                  "id": "sortBy",
                  "options": {
                     "fields": { },
                     "sort": [
                        {
                           "desc": true,
                           "field": "Value (last)"
                        }
                     ]
                  }
               },
               {
                  "id": "limit",
                  "options": {
                     "limitField": 5
                  }
               },
               {
                  "id": "organize",
                  "options": {
                     "excludeByName": { },
                     "indexByName": { },
                     "renameByName": {
                        "Value (last)": "Credits",
                        "instance": "Instance",
                        "name": "Warehouse"
                     }
                  }
               }
            ],
            "type": "table"
         },
         {
            "datasource": {
               "type": "prometheus",
               "uid": "${datasource}"
            },
            "description": "The top 5 databases that have the highest autoclustering credit usages.",
            "fieldConfig": {
               "overrides": [
                  {
                     "matcher": {
                        "id": "byName",
                        "options": "Credits"
                     },
                     "properties": [
                        {
                           "id": "unit",
                           "value": "credits/hr"
                        }
                     ]
                  }
               ]
            },
            "gridPos": {
               "h": 8,
               "w": 12,
               "x": 0,
               "y": 58
            },
            "id": 16,
            "options": {
               "showHeader": true
            },
            "pluginVersion": "v11.0.0",
            "targets": [
               {
                  "datasource": {
                     "type": "prometheus",
                     "uid": "${datasource}"
                  },
                  "expr": "sum by (job,instance, database_name) (snowflake_auto_clustering_credits{job=\"integrations/snowflake\",job=~\"$job\",instance=~\"$instance\"})",
                  "format": "table",
                  "instant": true,
                  "legendFormat": "{{instance}}",
                  "refId": "Database autoclustering credits used"
               }
            ],
            "title": "Top 5 database autoclustering credits used",
            "transformations": [
               {
                  "id": "groupBy",
                  "options": {
                     "fields": {
                        "Value": {
                           "aggregations": [
                              "last"
                           ],
                           "operation": "aggregate"
                        },
                        "database_name": {
                           "aggregations": [ ],
                           "operation": "groupby"
                        },
                        "instance": {
                           "aggregations": [ ],
                           "operation": "groupby"
                        }
                     }
                  }
               },
               {
                  "id": "sortBy",
                  "options": {
                     "fields": { },
                     "sort": [
                        {
                           "desc": true,
                           "field": "Value (last)"
                        }
                     ]
                  }
               },
               {
                  "id": "limit",
                  "options": {
                     "limitField": 5
                  }
               },
               {
                  "id": "organize",
                  "options": {
                     "excludeByName": { },
                     "indexByName": {
                        "Value (last)": 2,
                        "database_name": 1,
                        "instance": 0
                     },
                     "renameByName": {
                        "Value (last)": "Credits",
                        "database_name": "Database",
                        "instance": "Instance"
                     }
                  }
               }
            ],
            "type": "table"
         },
         {
            "datasource": {
               "type": "prometheus",
               "uid": "${datasource}"
            },
            "description": "The top 5 tables that have the highest autoclustering credit usages.",
            "fieldConfig": {
               "overrides": [
                  {
                     "matcher": {
                        "id": "byName",
                        "options": "Credits"
                     },
                     "properties": [
                        {
                           "id": "unit",
                           "value": "credits/hr"
                        }
                     ]
                  }
               ]
            },
            "gridPos": {
               "h": 8,
               "w": 12,
               "x": 12,
               "y": 58
            },
            "id": 17,
            "options": {
               "showHeader": true
            },
            "pluginVersion": "v11.0.0",
            "targets": [
               {
                  "datasource": {
                     "type": "prometheus",
                     "uid": "${datasource}"
                  },
                  "expr": "snowflake_auto_clustering_credits{job=\"integrations/snowflake\",job=~\"$job\",instance=~\"$instance\"}",
                  "format": "table",
                  "instant": true,
                  "legendFormat": "{{instance}}",
                  "refId": "Table autoclustering credits used"
               }
            ],
            "title": "Top 5 table autoclustering credits used",
            "transformations": [
               {
                  "id": "groupBy",
                  "options": {
                     "fields": {
                        "Value": {
                           "aggregations": [
                              "last"
                           ],
                           "operation": "aggregate"
                        },
                        "database_name": {
                           "aggregations": [ ],
                           "operation": "groupby"
                        },
                        "instance": {
                           "aggregations": [ ],
                           "operation": "groupby"
                        },
                        "schema_name": {
                           "aggregations": [ ],
                           "operation": "groupby"
                        },
                        "table_name": {
                           "aggregations": [ ],
                           "operation": "groupby"
                        }
                     }
                  }
               },
               {
                  "id": "sortBy",
                  "options": {
                     "fields": { },
                     "sort": [
                        {
                           "desc": true,
                           "field": "Value (last)"
                        }
                     ]
                  }
               },
               {
                  "id": "limit",
                  "options": {
                     "limitField": 5
                  }
               },
               {
                  "id": "organize",
                  "options": {
                     "excludeByName": { },
                     "indexByName": {
                        "Value (last)": 4,
                        "database_name": 1,
                        "instance": 0,
                        "schema_name": 2,
                        "table_name": 3
                     },
                     "renameByName": {
                        "Value (last)": "Credits",
                        "database_name": "Database",
                        "instance": "Instance",
                        "schema_name": "Schema",
                        "table_name": "Table"
                     }
                  }
               }
            ],
            "type": "table"
         }
      ],
      "refresh": "30m",
      "schemaVersion": 39,
      "tags": [
         "snowflake-mixin"
      ],
      "templating": {
         "list": [
            {
               "label": "Data source",
               "name": "datasource",
               "query": "prometheus",
               "regex": "",
               "type": "datasource"
            },
            {
               "allValue": ".+",
               "datasource": {
                  "type": "prometheus",
                  "uid": "${datasource}"
               },
               "includeAll": true,
               "label": "Job",
               "multi": true,
               "name": "job",
               "query": "label_values(snowflake_successful_login_rate{job=\"integrations/snowflake\"}, job)",
               "refresh": 2,
               "sort": 1,
               "type": "query"
            },
            {
               "allValue": ".+",
               "datasource": {
                  "type": "prometheus",
                  "uid": "${datasource}"
               },
               "includeAll": true,
               "label": "Exporter instance",
               "multi": true,
               "name": "instance",
               "query": "label_values(snowflake_successful_login_rate{job=\"integrations/snowflake\",job=~\"$job\"}, instance)",
               "refresh": 2,
               "sort": 1,
               "type": "query"
            }
         ]
      },
      "time": {
         "from": "now-8h",
         "to": "now"
      },
      "timezone": "default",
      "title": "Snowflake overview",
      "uid": "snowflake_overview"
   }